rhymex/__init__.py
rhymex/hyperparams.py
rhymex/stress_model.py
rhymex/syllables.py
rhymex/utils.py
rhymex/word_profile.py
rhymex/model/model.h5
rhymex/model/tokenizer.bin
rhymex/model/weights.h5
rhymex/vocabs/all_forms.rar
rhymex-0.0.4.dist-info/LICENSE
rhymex-0.0.4.dist-info/METADATA
rhymex-0.0.4.dist-info/WHEEL
rhymex-0.0.4.dist-info/top_level.txt
rhymex-0.0.4.dist-info/RECORD
