Metadata-Version: 2.1
Name: rhymex
Version: 0.0.4
Summary: Rhymex: library for analyzing russian words. Finding syllabuses and stresses in words
Home-page: https://gitlab.com/MaxN/rhymex
Author: Max Nedelchev
Author-email: max.nedelchev@gmail.com
License: UNKNOWN
Platform: UNKNOWN
Classifier: Programming Language :: Python :: 3
Classifier: License :: OSI Approved :: MIT License
Classifier: Operating System :: OS Independent
